llm_workers/api.py
llm_workers/cache.py
llm_workers/chat_history.py
llm_workers/cli_lib.py
llm_workers/config.py
llm_workers/cost_calculation.py
llm_workers/default-anthropic-models.yaml
llm_workers/default-google-models.yaml
llm_workers/default-openai-models.yaml
llm_workers/default-openai-old-models.yaml
llm_workers/expressions.py
llm_workers/generic-assistant.yaml
llm_workers/starlark.py
llm_workers/token_tracking.py
llm_workers/tools/custom_tool.py
llm_workers/tools/fetch.py
llm_workers/tools/fs.py
llm_workers/tools/llm_tool.py
llm_workers/tools/misc.py
llm_workers/tools/unsafe.py
llm_workers/user_context.py
llm_workers/utils.py
llm_workers/worker.py
llm_workers/worker_utils.py
llm_workers/workers_context.py
llm_workers-1.0.0.dist-info/METADATA
llm_workers-1.0.0.dist-info/WHEEL
llm_workers-1.0.0.dist-info/RECORD
